aws_schema_registry/__init__.py
aws_schema_registry/avro.py
aws_schema_registry/client.py
aws_schema_registry/codec.py
aws_schema_registry/exception.py
aws_schema_registry/jsonschema.py
aws_schema_registry/naming.py
aws_schema_registry/schema.py
aws_schema_registry/serde.py
aws_schema_registry/adapter/__init__.py
aws_schema_registry/adapter/kafka.py
aws_glue_schema_registry-1.1.3.dist-info/LICENSE
aws_glue_schema_registry-1.1.3.dist-info/METADATA
aws_glue_schema_registry-1.1.3.dist-info/WHEEL
aws_glue_schema_registry-1.1.3.dist-info/top_level.txt
aws_glue_schema_registry-1.1.3.dist-info/RECORD
