Metadata-Version: 2.1
Name: aws-glue-schema-registry
Version: 1.1.3
Summary: Use the AWS Glue Schema Registry.
Author: Corentin Debost
Author-email: develop@disasteraware.com
License: Apache Software License
Project-URL: Source, https://github.com/DisasterAWARE/aws-glue-schema-registry-python
Keywords: aws,glue,schema,registry,avro
Classifier: Development Status :: 4 - Beta
Classifier: Intended Audience :: Developers
Classifier: License :: OSI Approved :: Apache Software License
Classifier: Programming Language :: Python :: 3
Classifier: Programming Language :: Python :: 3 :: Only
Classifier: Programming Language :: Python :: 3.8
Classifier: Programming Language :: Python :: 3.9
Classifier: Programming Language :: Python :: 3.10
Classifier: Programming Language :: Python :: 3.11
Classifier: Topic :: Software Development :: Libraries
Classifier: Typing :: Typed
Requires-Python: >=3.8
License-File: LICENSE
Requires-Dist: boto3 >=1.17.102
Requires-Dist: fastavro >=1.4.5
Requires-Dist: fastjsonschema ~=2.15
Requires-Dist: orjson ~=3.6.0 ; python_version < "3.11"
Requires-Dist: typing-extensions >=3.7.4.3 ; python_version < "3.8"
Requires-Dist: orjson >=3.7.7 ; python_version >= "3.11"
Provides-Extra: dev
Requires-Dist: pytest >=6 ; extra == 'dev'
Requires-Dist: flake8 >=3 ; extra == 'dev'
Provides-Extra: kafka-python
Requires-Dist: kafka-python >=2 ; extra == 'kafka-python'
